Workbook
Name aporte: Planilha1!$D$18
Name patrimonio: Planilha1!$D$21
Name qntdAnos: Planilha1!$D$19
Name rendimentoCarteira: Planilha1!$D$13
Name salario: Planilha1!$D$12
Name sugestaoInvestimento: Planilha1!$D$14
Name taxaMensal: Planilha1!$D$20

Sheet Planilha1
B11: CONFIGURAÇÕES
B12: Salário | D12: 2000
B13: Rendimento de Carteira | D13: 0.006
B14: Sugestão de Investimento (30%) | D14: =D12*30% -> 600
B17: INVESTIMENTO MENSAL
A18: 2 | B18: Quanto investir por mês? | D18: 200
A19: 5 | B19: Por quantos anos? | D19: 5
A20: 10 | B20: Qual a taxa de rendimento mensal? | D20: 0.0108
A21: 20 | B21: Patrimônio Acumulado | D21: =FV(taxaMensal,qntdAnos*12,aporte*-1) -> 16760.804
A22: 30 | B22: Dividendos Mensais | D22: =patrimonio*rendimentoCarteira -> 100.56482
B25: CENÁRIOS | D25: DIVIDENDO
B26: Quanto em 2 anos? | C26: =FV($D$20,$A18*12,$D$18*-1) -> 5446.1727 | D26: =C26*rendimentoCarteira -> 32.677036
B27: Quanto em 5 anos? | C27: =FV($D$20,$A19*12,$D$18*-1) -> 16760.804 | D27: =C27*rendimentoCarteira -> 100.56482
B28: Quanto em 10 anos? | C28: =FV($D$20,$A20*12,$D$18*-1) -> 48691.533 | D28: =C28*rendimentoCarteira -> 292.1492
B29: Quanto em 20 anos? | C29: =FV($D$20,$A21*12,$D$18*-1) -> 225409.8 | D29: =C29*rendimentoCarteira -> 1352.4588
B30: Quanto em 30 anos? | C30: =FV($D$20,$A22*12,$D$18*-1) -> 866780.96 | D30: =C30*rendimentoCarteira -> 5200.6858
B33: PERFIL | C33: AGRESSIVO
B34: VALOR A SER INVESTIDO MENSALMENTE | C34: =aporte -> 200
B36: TIPO DE FII | C36: PERCENTUAL SUGERIDO | D36: VALORES
B37: PAPEL | C37: =VLOOKUP($C$33&"-"&B37,Planilha2!$A:$D,4,0) -> 0.5 | D37: =C37*$C$34 -> 100
B38: TIJOLO | C38: =VLOOKUP($C$33&"-"&B38,Planilha2!$A:$D,4,0) -> 0.1 | D38: =C38*$C$34 -> 20
B39: HIBRÍDOS | C39: =VLOOKUP($C$33&"-"&B39,Planilha2!$A:$D,4,0) -> 0.05 | D39: =C39*$C$34 -> 10
B40: FOFs | C40: =VLOOKUP($C$33&"-"&B40,Planilha2!$A:$D,4,0) -> 0.05 | D40: =C40*$C$34 -> 10
B41: DESENVOLVIMENTO | C41: =VLOOKUP($C$33&"-"&B41,Planilha2!$A:$D,4,0) -> 0.2 | D41: =C41*$C$34 -> 40
B42: HOTELARIAS | C42: =VLOOKUP($C$33&"-"&B42,Planilha2!$A:$D,4,0) -> 0.1 | D42: =C42*$C$34 -> 20
D43: =SUM(D37:D42) -> 200

Sheet Planilha2
A2: CHAVE | B2: PERFIL | C2: TIPO DE FII | D2: %
A3: =$B$3&"-"&C3 -> Conservador-PAPEL | B3: Conservador | C3: PAPEL | D3: 0.3
A4: =$B$3&"-"&C4 -> Conservador-TIJOLO | B4: Conservador | C4: TIJOLO | D4: 0.5 | H4: %
A5: =$B$3&"-"&C5 -> Conservador-HIBRÍDOS | B5: Conservador | C5: HIBRÍDOS | D5: 0.1 | G5: Conservador-TIJOLO | H5: =VLOOKUP(G5,$A:$D,4,0) -> 0.5
A6: =$B$3&"-"&C6 -> Conservador-FOFs | B6: Conservador | C6: FOFs | D6: 0.1
A7: =$B$3&"-"&C7 -> Conservador-DESENVOLVIMENTO | B7: Conservador | C7: DESENVOLVIMENTO | D7: 0
A8: =$B$3&"-"&C8 -> Conservador-HOTELARIAS | B8: Conservador | C8: HOTELARIAS | D8: 0
A9: =$B$9&"-"&C9 -> Moderado-PAPEL | B9: Moderado | C9: PAPEL | D9: 0.32
A10: =$B$9&"-"&C10 -> Moderado-TIJOLO | B10: Moderado | C10: TIJOLO | D10: 0.35
A11: =$B$9&"-"&C11 -> Moderado-HIBRÍDOS | B11: Moderado | C11: HIBRÍDOS | D11: 0.08
A12: =$B$9&"-"&C12 -> Moderado-FOFs | B12: Moderado | C12: FOFs | D12: 0.05
A13: =$B$9&"-"&C13 -> Moderado-DESENVOLVIMENTO | B13: Moderado | C13: DESENVOLVIMENTO | D13: 0.1
A14: =$B$9&"-"&C14 -> Moderado-HOTELARIAS | B14: Moderado | C14: HOTELARIAS | D14: 0.1
A15: =$B$15&"-"&C15 -> Agressivo-PAPEL | B15: Agressivo | C15: PAPEL | D15: 0.5
A16: =$B$15&"-"&C16 -> Agressivo-TIJOLO | B16: Agressivo | C16: TIJOLO | D16: 0.1
A17: =$B$15&"-"&C17 -> Agressivo-HIBRÍDOS | B17: Agressivo | C17: HIBRÍDOS | D17: 0.05
A18: =$B$15&"-"&C18 -> Agressivo-FOFs | B18: Agressivo | C18: FOFs | D18: 0.05
A19: =$B$15&"-"&C19 -> Agressivo-DESENVOLVIMENTO | B19: Agressivo | C19: DESENVOLVIMENTO | D19: 0.2
A20: =$B$15&"-"&C20 -> Agressivo-HOTELARIAS | B20: Agressivo | C20: HOTELARIAS | D20: 0.1
